grid_measure/__init__.py
grid_measure/cli.py
grid_measure/core.py
grid_measure/defaults.py
grid_measure-0.1.0.dist-info/entry_points.txt
grid_measure-0.1.0.dist-info/WHEEL
grid_measure-0.1.0.dist-info/METADATA
grid_measure-0.1.0.dist-info/RECORD
