Metadata-Version: 2.1
Name: grid-measure
Version: 0.1.0
Summary: A tool for measuring the scale of grid paper.
Author: TankredO
Author-email: tankred.ott@ur.de
Requires-Python: >=3.8,<3.12
Classifier: Programming Language :: Python :: 3
Classifier: Programming Language :: Python :: 3.10
Classifier: Programming Language :: Python :: 3.8
Classifier: Programming Language :: Python :: 3.9
Requires-Dist: cloup (>=1.0.1,<2.0.0)
Requires-Dist: deskew (>=1.3.3,<2.0.0)
Requires-Dist: matplotlib (>=3.6.1,<4.0.0)
Requires-Dist: numpy (>=1.23.4,<2.0.0)
Requires-Dist: opencv-python (>=4.6.0,<5.0.0)
Requires-Dist: pandas (>=1.5.1,<2.0.0)
Requires-Dist: scikit-image (>=0.19.3,<0.20.0)
Requires-Dist: scikit-learn (>=1.1.3,<2.0.0)
Requires-Dist: tqdm (>=4.64.1,<5.0.0)
